chekml_blackemperor/__init__.py
chekml_blackemperor/cli.py
chekml_blackemperor/config.py
chekml_blackemperor/models.py
chekml_blackemperor/server.py
chekml_blackemperor/utils.py
chekml_blackemperor/worker.py
chekml_blackemperor/aggregation/__init__.py
chekml_blackemperor/aggregation/base.py
chekml_blackemperor/aggregation/custom.py
chekml_blackemperor/aggregation/distributed.py
chekml_blackemperor/aggregation/federated.py
chekml_blackemperor/aggregation/hybrid.py
chekml_blackemperor-0.1.1.dist-info/METADATA
chekml_blackemperor-0.1.1.dist-info/WHEEL
chekml_blackemperor-0.1.1.dist-info/entry_points.txt
chekml_blackemperor-0.1.1.dist-info/top_level.txt
chekml_blackemperor-0.1.1.dist-info/RECORD
