Metadata-Version: 2.4
Name: chekml-blackemperor
Version: 0.1.1
Requires-Dist: torch>=1.9.0
Requires-Dist: torchvision>=0.10.0
Requires-Dist: aiohttp>=3.8.0
Requires-Dist: websockets>=10.0
Requires-Dist: google-api-python-client>=2.0.0
Requires-Dist: google-auth-httplib2>=0.1.0
Requires-Dist: google-auth-oauthlib>=0.4.0
Requires-Dist: gdown>=4.0.0
Dynamic: requires-dist
